ads_napari/__init__.py
ads_napari/_widget.py
ads_napari/napari.yaml
ads_napari/settings_menu_ui.py
ads_napari-0.0.5.dist-info/METADATA
ads_napari-0.0.5.dist-info/WHEEL
ads_napari-0.0.5.dist-info/entry_points.txt
ads_napari-0.0.5.dist-info/top_level.txt
ads_napari-0.0.5.dist-info/RECORD
