Metadata-Version: 2.2
Name: ads_napari
Version: 0.0.5
Summary: Axon/Myelin segmentation using AI
Author: NeuroPoly Lab
Author-email: axondeepseg@googlegroups.com
Project-URL: Bug Tracker, https://github.com/axondeepseg/ads_napari/issues
Project-URL: Documentation, https://github.com/axondeepseg/ads_napari#README.md
Project-URL: Source Code, https://github.com/axondeepseg/ads_napari
Project-URL: User Support, https://github.com/axondeepseg/ads_napari/issues
Classifier: Development Status :: 2 - Pre-Alpha
Classifier: Framework :: napari
Classifier: Intended Audience :: Developers
Classifier: License :: OSI Approved :: MIT License
Classifier: Operating System :: OS Independent
Classifier: Programming Language :: Python
Classifier: Programming Language :: Python :: 3
Classifier: Programming Language :: Python :: 3 :: Only
Classifier: Programming Language :: Python :: 3.11
Classifier: Programming Language :: Python :: 3.12
Classifier: Topic :: Scientific/Engineering :: Image Processing
Requires-Python: >=3.11
Requires-Dist: numpy
Requires-Dist: magicgui
Requires-Dist: qtpy
Requires-Dist: scikit-image
Requires-Dist: ads-base
Provides-Extra: testing
Requires-Dist: tox; extra == "testing"
Requires-Dist: pytest; extra == "testing"
Requires-Dist: pytest-cov; extra == "testing"
Requires-Dist: pytest-qt; extra == "testing"
Requires-Dist: napari; extra == "testing"
Requires-Dist: pyqt5; extra == "testing"
